pytalentsolution/__init__.py
pytalentsolution/client_event.py
pytalentsolution/company.py
pytalentsolution/config.py
pytalentsolution/cts.py
pytalentsolution/job.py
pytalentsolution/job_search.py
pytalentsolution/profile.py
pytalentsolution/tenant.py
pytalentsolution-0.4.0.dist-info/LICENSE.md
pytalentsolution-0.4.0.dist-info/METADATA
pytalentsolution-0.4.0.dist-info/WHEEL
pytalentsolution-0.4.0.dist-info/RECORD
