Metadata-Version: 2.1
Name: pytalentsolution
Version: 0.4.0
Summary: 
License: ISC
Author: Nutchanon Ninyawee
Author-email: me@nutchanon.org
Requires-Python: >=3.8,<4.0
Classifier: License :: OSI Approved
Classifier: Programming Language :: Python :: 3
Classifier: Programming Language :: Python :: 3.8
Classifier: Programming Language :: Python :: 3.9
Classifier: Programming Language :: Python :: 3.10
Classifier: Programming Language :: Python :: 3.11
Requires-Dist: PyPika (>=0.43.0,<0.44.0)
Requires-Dist: fastapi-utils (>=0.2.1,<0.3.0)
Requires-Dist: google-cloud-talent (>=2.0.0,<3.0.0)
Requires-Dist: pydantic (>=1.5.1,<2.0.0)
Requires-Dist: python-dotenv (>=0.15.0,<0.16.0)
